Workbook
Name aporte: Investimento!$D$16
Name dividendos: Investimento!$D$20
Name patrimonio: Investimento!$D$19
Name qtd_anos: Investimento!$D$17
Name rendimento_carteira: Investimento!$D$12
Name salario: Investimento!$D$11
Name sugestao_investimento: Investimento!$D$13
Name taxa_mensal: Investimento!$D$18

Sheet Investimento
B10: BASE DE CÁLCULO
B11: Salário | D11: 7000
B12: Taxa mensal de dividendos | D12: 0.003
B13: Sugestão de Investimento (30%) | D13: =D11*30% -> 2100
B15: INVESTIMENTO MENSAL
B16: Quanto investir por mês ? | D16: 750
B17: Por Quantos Anos ? | D17: 3
B18: Taxa mensal de acumulação | D18: 0.0178
B19: Patrimônio acumulado ? | D19: =FV(taxa_mensal,qtd_anos*12,aporte*-1) -> 37387.542
B20: Dividendos Mensais ? | D20: =patrimonio*rendimento_carteira -> 112.16263
B22: PROJEÇÃO | D22: Dividendo
A23: 2 | B23: Quanto em 2 Anos ? | C23: =FV($D$18,$A23*12,-$D$16) -> 22213.898 | D23: =C23*rendimento_carteira -> 66.641695
A24: 5 | B24: Quanto em 5 Anos ? | C24: =FV($D$18,$A24*12,-$D$16) -> 79312.521 | D24: =C24*rendimento_carteira -> 237.93756
A25: 10 | B25: Quanto em 10 Anos ? | C25: =FV($D$18,$A25*12,-$D$16) -> 307919.01 | D25: =C25*rendimento_carteira -> 923.75702
A26: 20 | B26: Quanto em 20 Anos ? | C26: =FV($D$18,$A26*12,-$D$16) -> 2866093 | D26: =C26*rendimento_carteira -> 8598.2791
A27: 30 | B27: Quanto em 30 Anos ? | C27: =FV($D$18,$A27*12,-$D$16) -> 24119261 | D27: =C27*rendimento_carteira -> 72357.782
B32: PERFIL | C32: Conservador
B33: VALOR A SER INVESTIDO POR MÊS | C33: =aporte -> 750
B35: TIPO DE FII | C35: Percentual Sugerido | D35: Valores
B36: PAPEL | C36: =VLOOKUP($C$32&"-"&B36,Perfis!$A$3:$D$20,4,FALSE) -> 0.25 | D36: =C36*$C$33 -> 187.5
B37: TIJOLO | C37: =VLOOKUP($C$32&"-"&B37,Perfis!$A$3:$D$20,4,FALSE) -> 0.35 | D37: =C37*$C$33 -> 262.5
B38: HÍBRIDOS | C38: =VLOOKUP($C$32&"-"&B38,Perfis!$A$3:$D$20,4,FALSE) -> 0.15 | D38: =C38*$C$33 -> 112.5
B39: FOFs | C39: =VLOOKUP($C$32&"-"&B39,Perfis!$A$3:$D$20,4,FALSE) -> 0.12 | D39: =C39*$C$33 -> 90
B40: DESENVOLVIMENTO | C40: =VLOOKUP($C$32&"-"&B40,Perfis!$A$3:$D$20,4,FALSE) -> 0.08 | D40: =C40*$C$33 -> 60
B41: HOTELARIAS | C41: =VLOOKUP($C$32&"-"&B41,Perfis!$A$3:$D$20,4,FALSE) -> 0.05 | D41: =C41*$C$33 -> 37.5
B42: TOTAL | C42: =SUM(C36:C41) -> 1 | D42: =SUM(D36:D41) -> 750
B44: Preencha as células brancas. As células cinzas são calculadas.
B45: D18: taxa usada para acumular patrimônio. D12: taxa dos dividendos mensais.
B46: Premissas de simulação: taxas constantes e aportes ao fim de cada mês.

Sheet Perfis
A2: CHAVE | B2: PERFIL | C2: TIPO DE FII | D2: % | G2: =A2 -> CHAVE | H2: %
A3: =B3&"-"&C3 -> Conservador-PAPEL | B3: Conservador | C3: PAPEL | D3: 0.25 | G3: Moderado-TIJOLO | H3: =VLOOKUP(G3,$A$3:$D$20,4,FALSE) -> 0.4
A4: =B4&"-"&C4 -> Conservador-TIJOLO | B4: Conservador | C4: TIJOLO | D4: 0.35
A5: =B5&"-"&C5 -> Conservador-HÍBRIDOS | B5: Conservador | C5: HÍBRIDOS | D5: 0.15
A6: =B6&"-"&C6 -> Conservador-FOFs | B6: Conservador | C6: FOFs | D6: 0.12
A7: =B7&"-"&C7 -> Conservador-DESENVOLVIMENTO | B7: Conservador | C7: DESENVOLVIMENTO | D7: 0.08
A8: =B8&"-"&C8 -> Conservador-HOTELARIAS | B8: Conservador | C8: HOTELARIAS | D8: 0.05
A9: =B9&"-"&C9 -> Moderado-PAPEL | B9: Moderado | C9: PAPEL | D9: 0.2
A10: =B10&"-"&C10 -> Moderado-TIJOLO | B10: Moderado | C10: TIJOLO | D10: 0.4
A11: =B11&"-"&C11 -> Moderado-HÍBRIDOS | B11: Moderado | C11: HÍBRIDOS | D11: 0.12
A12: =B12&"-"&C12 -> Moderado-FOFs | B12: Moderado | C12: FOFs | D12: 0.15
A13: =B13&"-"&C13 -> Moderado-DESENVOLVIMENTO | B13: Moderado | C13: DESENVOLVIMENTO | D13: 0.1
A14: =B14&"-"&C14 -> Moderado-HOTELARIAS | B14: Moderado | C14: HOTELARIAS | D14: 0.03
A15: =B15&"-"&C15 -> Agressivo-PAPEL | B15: Agressivo | C15: PAPEL | D15: 0.15
... A20: =B20&"-"&C20 -> Agressivo-HOTELARIAS | B20: Agressivo | C20: HOTELARIAS | D20: 0.09
